Metadata-Version: 2.1
Name: wltp-gearshift
Version: 1.4.0
Summary: Gearshift tool implement the Sub-Annex 1 and Sub-Annex 2 of theCOMMISSION REGULATION (EU) 2017/1151 of 1 June 2017 - Annex XXI
Home-page: UNKNOWN
Author: GEARSHIFT-Team
Author-email: jrc-ldvs-co2@ec.europa.eu
License: EUPL 1.1+
Keywords: GEARSHIFT,WLTP,vehicle,automotive,EU,JRC,IET,policy,monitoring,simulator
Platform: any
Classifier: Programming Language :: Python
Classifier: Programming Language :: Python :: 3
Classifier: Programming Language :: Python :: 3.6
Classifier: Programming Language :: Python :: 3.7
Classifier: Programming Language :: Python :: Implementation :: CPython
Classifier: Development Status :: 7 - Inactive
Classifier: Natural Language :: English
Classifier: Intended Audience :: Developers
Classifier: Intended Audience :: Science/Research
Classifier: Intended Audience :: Manufacturing
Classifier: Environment :: Console
Classifier: License :: OSI Approved :: European Union Public Licence 1.1 (EUPL 1.1)
Classifier: Natural Language :: English
Classifier: Operating System :: MacOS :: MacOS X
Classifier: Operating System :: Microsoft :: Windows
Classifier: Operating System :: POSIX
Classifier: Operating System :: Unix
Classifier: Operating System :: OS Independent
Classifier: Topic :: Scientific/Engineering
Classifier: Topic :: Scientific/Engineering :: Information Analysis
Requires-Python: >=3.5
Requires-Dist: jrshift
